pygments_sb_nrql/__init__.py
pygments_sb_nrql/_modidx.py
pygments_sb_nrql/builtins.py
pygments_sb_nrql/lexer.py
pygments_sb_nrql/version.py
pygments_sb_nrql-0.7.0.dist-info/LICENSE.txt
pygments_sb_nrql-0.7.0.dist-info/METADATA
pygments_sb_nrql-0.7.0.dist-info/WHEEL
pygments_sb_nrql-0.7.0.dist-info/entry_points.txt
pygments_sb_nrql-0.7.0.dist-info/RECORD
