Metadata-Version: 2.3
Name: pygments-sb-nrql
Version: 0.7.0
Summary: New Relic SDK to interact with Nerdgraph API.
License: MIT
Keywords: Softbutterfly,New Relic,SDK
Author: Dynova Development Team
Author-email: dev@dynova.io
Maintainer: zodiacfireworks
Maintainer-email: martin.vuelta@gmail.com
Requires-Python: >=3.9.0,<4.0.0
Classifier: Development Status :: 5 - Production/Stable
Classifier: Intended Audience :: Developers
Classifier: Intended Audience :: Information Technology
Classifier: Intended Audience :: System Administrators
Classifier: License :: OSI Approved :: MIT License
Classifier: Natural Language :: English
Classifier: Programming Language :: Python :: 3.10
Classifier: Programming Language :: Python :: 3.11
Classifier: Programming Language :: Python :: 3.12
Classifier: Programming Language :: Python :: 3.9
Classifier: Topic :: Documentation
Classifier: Topic :: Software Development :: Documentation
Classifier: Topic :: Software Development :: Libraries :: Python Modules
Classifier: Topic :: Software Development :: Libraries
Classifier: Topic :: Software Development
Classifier: Topic :: System
Classifier: Topic :: Text Processing :: Markup
Classifier: Topic :: Utilities
Requires-Dist: pygments (>=2.19.1,<3.0.0)
Project-URL: Bug Tracker, https://github.com/dynovaio/newrelic-sb-nrql-pygments/issues
Project-URL: Changelog, https://github.com/dynovaio/newrelic-sb-nrql-pygments/blob/master/CHANGELOG.md
Project-URL: Documentation, https://dynovaio.github.io/newrelic-sb-nrql-pygments
Project-URL: Download, https://github.com/dynovaio/newrelic-sb-nrql-pygments/archive/refs/tags/v0.7.0.zip
Project-URL: Homepage, https://github.com/dynovaio/newrelic-sb-nrql-pygments
Project-URL: Issues, https://github.com/dynovaio/newrelic-sb-nrql-pygments/issues
Project-URL: Repository, https://github.com/dynovaio/newrelic-sb-nrql-pygments
